single_cell_tools/__init__.py
single_cell_tools/compare_clusters.py
single_cell_tools/create_seurat_from_triska_data.R
single_cell_tools/genes_correlated_with_pseudotime_interactive.py
single_cell_tools/gtfs_to_TPM-FPKM.py
single_cell_tools/import_gtf.py
single_cell_tools/plotly_heatmap.py
single_cell_tools/pseudotime_interactive.py
single_cell_tools/sc_pseudotime.py
single_cell_tools/single-cell-tools.py
single_cell_tools/utils.py
single_cell_tools/velocyto_test.py
single_cell_tools-0.1.1.dist-info/LICENSE
single_cell_tools-0.1.1.dist-info/WHEEL
single_cell_tools-0.1.1.dist-info/METADATA
single_cell_tools-0.1.1.dist-info/RECORD
