Metadata-Version: 2.1
Name: single-cell-tools
Version: 0.1.1
Summary: A package for pseudotime and dimension reduction by cluster centroids
Home-page: https://github.com/whtns/single-cell-tools
License: MIT
Author: Kevin Stachelek
Requires-Python: >=3.8,<4.0
Classifier: License :: OSI Approved :: MIT License
Classifier: Programming Language :: Python :: 3
Classifier: Programming Language :: Python :: 3.8
Classifier: Programming Language :: Python :: 3.9
Requires-Dist: pandas (>=1.2.3,<2.0.0)
Project-URL: Documentation, https://single-cell-tools.readthedocs.io/en/latest/
Project-URL: Repository, https://github.com/whtns/single-cell-tools
